open_trivia_database_wrapper-0.3.2.dist-info/licenses/LICENSE
opentdb/__init__.py
opentdb/enums.py
opentdb/models.py
opentdb/opentdb.py
open_trivia_database_wrapper-0.3.2.dist-info/METADATA
open_trivia_database_wrapper-0.3.2.dist-info/WHEEL
open_trivia_database_wrapper-0.3.2.dist-info/top_level.txt
open_trivia_database_wrapper-0.3.2.dist-info/RECORD
